CHANGES.txt
MANIFEST.in
README.rst
buildout.cfg
minitage.cfg
setup.cfg
setup.py
src/minitage/__init__.py
src/minitage.paste.egg-info/PKG-INFO
src/minitage.paste.egg-info/SOURCES.txt
src/minitage.paste.egg-info/dependency_links.txt
src/minitage.paste.egg-info/entry_points.txt
src/minitage.paste.egg-info/namespace_packages.txt
src/minitage.paste.egg-info/not-zip-safe
src/minitage.paste.egg-info/requires.txt
src/minitage.paste.egg-info/top_level.txt
src/minitage/paste/__init__.py
src/minitage/paste/common/__init__.py
src/minitage/paste/instances/__init__.py
src/minitage/paste/instances/apache/__init__.py
src/minitage/paste/instances/apache/wrapper.py
src/minitage/paste/instances/apache/template/bin/+project+.ab_tmpl
src/minitage/paste/instances/apache/template/bin/+project+.apachectl_tmpl
src/minitage/paste/instances/apache/template/bin/+project+.apxs_tmpl
src/minitage/paste/instances/apache/template/bin/+project+.checkgid_tmpl
src/minitage/paste/instances/apache/template/bin/+project+.dbmmanage_tmpl
src/minitage/paste/instances/apache/template/bin/+project+.envvars-std_tmpl
src/minitage/paste/instances/apache/template/bin/+project+.envvars_tmpl
src/minitage/paste/instances/apache/template/bin/+project+.htcacheclean_tmpl
src/minitage/paste/instances/apache/template/bin/+project+.htdbm_tmpl
src/minitage/paste/instances/apache/template/bin/+project+.htdigest_tmpl
src/minitage/paste/instances/apache/template/bin/+project+.htpasswd_tmpl
src/minitage/paste/instances/apache/template/bin/+project+.httpd_tmpl
src/minitage/paste/instances/apache/template/bin/+project+.httxt2dbm_tmpl
src/minitage/paste/instances/apache/template/bin/+project+.logresolve_tmpl
src/minitage/paste/instances/apache/template/bin/+project+.rotatelogs_tmpl
src/minitage/paste/instances/apache/template/bin/+project+.suexec_tmpl
src/minitage/paste/instances/apache/template/etc/apache/+project+/httpd.conf_tmpl
src/minitage/paste/instances/apache/template/etc/apache/+project+/magic
src/minitage/paste/instances/apache/template/etc/apache/+project+/mime.types
src/minitage/paste/instances/apache/template/etc/apache/+project+/extra/httpd-autoindex.conf_tmpl
src/minitage/paste/instances/apache/template/etc/apache/+project+/extra/httpd-dav.conf_tmpl
src/minitage/paste/instances/apache/template/etc/apache/+project+/extra/httpd-default.conf
