Metadata-Version: 1.1
Name: minitage.paste
Version: 1.4.6
Summary: PasteScripts to facilitate use of minitage and creation of minitage based projects sponsored by Makina Corpus.
Home-page: http://cheeseshop.python.org/pypi/minitage.paste
Author: Mathieu Pasquet
Author-email: kiorky@cryptelium.net
License: BSD
Keywords: PasteScripts minitage
Platform: UNKNOWN
Classifier: Framework :: Django
Classifier: Framework :: Pylons
Classifier: Framework :: Paste
Classifier: Framework :: Plone
Classifier: Framework :: Zope2
Classifier: Framework :: Zope3
Classifier: Framework :: Buildout
Classifier: Intended Audience :: Developers
Classifier: License :: OSI Approved :: BSD License
Classifier: Topic :: Software Development :: Build Tools
Classifier: Topic :: Software Development :: Libraries :: Python Modules
